LICENSE
MANIFEST.in
README.md
setup.py
testinweweewewe/__init__.py
testinweweewewe/api_helper.py
testinweweewewe/configuration.py
testinweweewewe/decorators.py
testinweweewewe/testinweweewewe_client.py
testinweweewewe.egg-info/PKG-INFO
testinweweewewe.egg-info/SOURCES.txt
testinweweewewe.egg-info/dependency_links.txt
testinweweewewe.egg-info/requires.txt
testinweweewewe.egg-info/top_level.txt
testinweweewewe/controllers/__init__.py
testinweweewewe/controllers/api_controller.py
testinweweewewe/controllers/base_controller.py
testinweweewewe/exceptions/__init__.py
testinweweewewe/exceptions/api_exception.py
testinweweewewe/http/__init__.py
testinweweewewe/http/http_call_back.py
testinweweewewe/http/http_client.py
testinweweewewe/http/http_context.py
testinweweewewe/http/http_method_enum.py
testinweweewewe/http/http_request.py
testinweweewewe/http/http_response.py
testinweweewewe/http/requests_client.py
testinweweewewe/http/auth/__init__.py
testinweweewewe/http/auth/o_auth_2.py
testinweweewewe/models/__init__.py
testinweweewewe/models/authentication_response.py
testinweweewewe/models/get_message_response.py
testinweweewewe/models/get_message_status_response.py
testinweweewewe/models/send_sms_response.py
testinweweewewe/models/send_sms_to_body_object.py
tests/__init__.py
tests/http_response_catcher.py
tests/test_helper.py
tests/controllers/__init__.py
tests/controllers/controller_test_base.py
tests/controllers/test_api_controller.py