Metadata-Version: 1.0
Name: testinweweewewe
Version: 2.0.0
Summary: The SMS API sends SMS messages to Australian mobile phones in a single request. This API allows you to send and receive messages. You can also query the status of a previously sent SMS message.  ## Authentication  This API uses OAuth v2 Bearer Token for its authentication.  The parameters that are needed to be sent for this type of authentication are as follows:  + `CONSUMER_KEY` - your consumer key  + `CONSUMER_SECRET` - your consumer secret
Home-page: https://apimatic.io
Author: APIMatic SDK Generator
Author-email: support@apimatic.io
License: UNKNOWN
Platform: UNKNOWN
